httpie_ovh_auth.py
httpie_ovh_auth-1.2.0.dist-info/LICENSE
httpie_ovh_auth-1.2.0.dist-info/METADATA
httpie_ovh_auth-1.2.0.dist-info/WHEEL
httpie_ovh_auth-1.2.0.dist-info/entry_points.txt
httpie_ovh_auth-1.2.0.dist-info/top_level.txt
httpie_ovh_auth-1.2.0.dist-info/RECORD
