Metadata-Version: 2.1
Name: httpie-ovh-auth
Version: 1.2.0
Summary: OVH auth plugin for HTTPie.
Author-email: Laurent Almeras <lalmeras@gmail.com>
License: BSD 3-Clause License
Project-URL: repository, https://github.com/lalmeras/httpie_ovh_auth/
Project-URL: homepage, https://pypi.org/project/httpie-ovh-auth/
Project-URL: changelog, https://github.com/lalmeras/httpie_ovh_auth/blob/dev/README.md
Classifier: Development Status :: 3 - Alpha
Classifier: Programming Language :: Python
Classifier: Programming Language :: Python :: 3
Classifier: Programming Language :: Python :: 3.7
Classifier: Programming Language :: Python :: 3.8
Classifier: Programming Language :: Python :: 3.9
Classifier: Programming Language :: Python :: 3.10
Classifier: Environment :: Plugins
Classifier: Environment :: Console
Classifier: Environment :: Web Environment
Classifier: Intended Audience :: Developers
Classifier: License :: OSI Approved :: BSD License
Classifier: Topic :: Internet :: WWW/HTTP
Classifier: Topic :: Utilities
Requires-Python: >=3.7
License-File: LICENSE
Requires-Dist: httpie (>=1.0.0)
Provides-Extra: dev
Requires-Dist: twine ; extra == 'dev'
Requires-Dist: tbump ; extra == 'dev'
Requires-Dist: ipdb ; extra == 'dev'
Requires-Dist: build ; extra == 'dev'
Requires-Dist: pypiserver ; extra == 'dev'
Requires-Dist: semver (<3) ; extra == 'dev'
Provides-Extra: test
Requires-Dist: tox ; extra == 'test'
Requires-Dist: mock (>=2.0.0) ; extra == 'test'
Requires-Dist: pexpect (>=4.2.1) ; extra == 'test'
Requires-Dist: pytest (>=3.0.6) ; extra == 'test'
Requires-Dist: pytest-cov (>=2.4.0) ; extra == 'test'
Requires-Dist: mypy ; extra == 'test'
Requires-Dist: pylint ; extra == 'test'
Requires-Dist: rope ; extra == 'test'
Requires-Dist: black (==20.8b1) ; extra == 'test'
